MySBdt/MySBdt.py
MySBdt/__init__.py
MySB_datatraffic-4.1.dist-info/METADATA
MySB_datatraffic-4.1.dist-info/WHEEL
MySB_datatraffic-4.1.dist-info/top_level.txt
MySB_datatraffic-4.1.dist-info/RECORD
