Metadata-Version: 2.1
Name: MySB-datatraffic
Version: 4.1
Summary: MySoftBank dataTraffic
Home-page: https://github.com/0x0u/MySB_dataTraffic
Author: m0zu
Author-email: m0zurillex@gmail.com
License: UNKNOWN
Keywords: Python3 MySoftBank
Platform: UNKNOWN
Requires-Dist: lxml
Requires-Dist: requests
Requires-Dist: beautifulsoup4
